reddit2md/__init__.py
reddit2md/exceptions.py
reddit2md/r2md.py
reddit2md/utils.py
reddit2md-0.2.0.dist-info/LICENSE
reddit2md-0.2.0.dist-info/METADATA
reddit2md-0.2.0.dist-info/WHEEL
reddit2md-0.2.0.dist-info/top_level.txt
reddit2md-0.2.0.dist-info/RECORD
