Metadata-Version: 2.1
Name: reddit2md
Version: 0.2.0
Summary: Useful towel-related stuff.
Home-page: https://github.com/lewisleedev/reddit2md
Author: Lewis Lee
Author-email: lewislee@lewislee.net
License: LICENSE
Platform: UNKNOWN
License-File: LICENSE
Requires-Dist: praw (>=7.3.0)
Requires-Dist: pytz (==2021.1)
